pyctr/__init__.py
pyctr/common.py
pyctr/fileio.py
pyctr/util.py
pyctr/crypto/__init__.py
pyctr/crypto/engine.py
pyctr/crypto/seeddb.py
pyctr/type/__init__.py
pyctr/type/cci.py
pyctr/type/cdn.py
pyctr/type/cia.py
pyctr/type/exefs.py
pyctr/type/nand.py
pyctr/type/ncch.py
pyctr/type/romfs.py
pyctr/type/sd.py
pyctr/type/sdtitle.py
pyctr/type/smdh.py
pyctr/type/tmd.py
pyctr/type/base/__init__.py
pyctr/type/base/typereader.py
pyctr/type/config/__init__.py
pyctr/type/config/blocks.py
pyctr/type/config/save.py
pyctr/type/save/__init__.py
pyctr/type/save/cmac.py
pyctr/type/save/common.py
pyctr/type/save/diff.py
pyctr/type/save/disa.py
pyctr/type/save/partition.py
pyctr/type/save/partdesc/__init__.py
pyctr/type/save/partdesc/common.py
pyctr/type/save/partdesc/difi.py
pyctr/type/save/partdesc/dpfs.py
pyctr/type/save/partdesc/ivfc.py
pyctr-0.7.5.dist-info/LICENSE
pyctr-0.7.5.dist-info/METADATA
pyctr-0.7.5.dist-info/WHEEL
pyctr-0.7.5.dist-info/top_level.txt
pyctr-0.7.5.dist-info/RECORD
