Metadata-Version: 2.1
Name: pyctr
Version: 0.7.5
Summary: Python library to parse several Nintendo 3DS files
Home-page: https://github.com/ihaveamac/pyctr
Author: Ian Burgwin
Author-email: ian@ianburgwin.net
License: MIT
Classifier: License :: OSI Approved :: MIT License
Classifier: Programming Language :: Python :: 3
Classifier: Programming Language :: Python :: 3.8
Classifier: Programming Language :: Python :: 3.9
Classifier: Programming Language :: Python :: 3.10
Classifier: Programming Language :: Python :: 3.11
License-File: LICENSE
Requires-Dist: pycryptodomex <4,>=3.9
Provides-Extra: images
Requires-Dist: Pillow >=8.2 ; extra == 'images'
